{
    "start_config": "random",
    "popsize": 500,
    "selection_strategy": "roulette",
    "initial_tp_gauss_dist": [
        2.0,
        0.5
    ],
    "initial_pt_gauss_dist": [
        2.0,
        0.5
    ],
    "initial_tt_gauss_dist": [
        8.0,
        1.0
    ],
    "initial_pe_gauss_dist": [
        2.0,
        0.5
    ],
    "initial_te_gauss_dist": [
        2.0,
        0.5
    ],
    "initial_as_gauss_dist": [
        2.0,
        0.5
    ],
    "species_boundary": 1.8,
    "coeff_disjoint": 1.2,
    "coeff_excess": 1.4,
    "coeff_matched": 0.5,
    "enough_gens_to_change_things": 10000,
    "update_species_rep": true,
    "leader_is_rep": true,
    "selection_threshold": 30,
    "spawn_cutoff": 0.7,
    "elitism": true,
    "prob_asex": 0.25,
    "allowed_gens_no_improvement": 10000,
    "old_age": 30,
    "old_penalty": 0.8,
    "youth_bonus": 1.4,
    "random_mating": true,
    "perc_fit_traces_weight": 1,
    "average_trace_fitness_weight": 0.5,
    "log_fitness_weight": 1,
    "soundness_weight": 0,
    "precision_weight": 0.0,
    "generalization_weight": 0.0,
    "simplicity_weight": 0.0,
    "fraction_used_trans_weight": 1,
    "fraction_tasks_weight": 0.0,
    "prob_t_p_arc": [
        0.1,
        0.3
    ],
    "prob_p_t_arc": [
        0.1,
        0.3
    ],
    "prob_t_t_conn": [
        0.05,
        0.2
    ],
    "prob_new_p": [
        0.07,
        0.3
    ],
    "prob_new_empty_t": [
        0.07,
        0.3
    ],
    "prob_split_arc": [
        0.05,
        0.2
    ],
    "prob_increase_arcs": [
        0.0,
        0.0
    ],
    "prob_remove_arc": [
        0.05,
        0.3
    ],
    "prob_prune_extensions": [
        0.05,
        0.4
    ],
    "is_no_preference_for_tasks": false,
    "prob_pick_empty_trans": 0.3,
    "num_trys_make_conn": 20,
    "prevent_chaining": true,
    "num_trys_split_arc": 10
}